xpyme/__init__.py
xpyme/__main__.py
xpyme/main.py
xpyme-0.2.0.dist-info/entry_points.txt
xpyme-0.2.0.dist-info/METADATA
xpyme-0.2.0.dist-info/WHEEL
xpyme-0.2.0.dist-info/RECORD
