Metadata-Version: 2.1
Name: xpyme
Version: 0.2.0
Summary: 
Author: Alaamer
Author-email: ahmedmuhmmed239@gmail.com
Requires-Python: >=3.11,<4.0
Classifier: Programming Language :: Python :: 3
Classifier: Programming Language :: Python :: 3.11
Classifier: Programming Language :: Python :: 3.12
